shapley_numba/__init__.py
shapley_numba/common.py
shapley_numba/core.py
shapley_numba/game_templates.py
shapley_numba/harsanyi.py
shapley_numba/harsanyi_large.py
shapley_numba/harsanyi_naive.py
shapley_numba/py.typed
shapley_numba/shapley.py
shapley_numba/tools.py
shapley_numba/typing.py
shapley_numba/examples/__init__.py
shapley_numba/examples/finance.py
shapley_numba/examples/games.py
shapley_numba-0.0.5.dist-info/METADATA
shapley_numba-0.0.5.dist-info/WHEEL
shapley_numba-0.0.5.dist-info/licenses/LICENSE
shapley_numba-0.0.5.dist-info/RECORD
