Metadata-Version: 2.4
Name: shapley-numba
Version: 0.0.5
Summary: Shapley-Numba - computations on cooperative games using Numba. Author and compute cooperative games with ease.  Package provides: - Shapley Values - Harsanyi Dividends (a.k.a. synergies)
Project-URL: repository, https://gitlab.com/shapley-numba/shapley-numba
Project-URL: documentation, https://shapley-numba-f859eb.gitlab.io/
Project-URL: issues, https://gitlab.com/shapley-numba/shapley-numba/-/issues
Author-email: Boris Ettinger <ettinger.boris@gmail.com>
License-Expression: MIT-0
License-File: LICENSE
Keywords: coalitional-games,computational-game-theory,cooperative-games,game-theory,harsanyi-dividends,numba,shapley-value,synergies
Classifier: Development Status :: 3 - Alpha
Classifier: Intended Audience :: Developers
Classifier: Intended Audience :: Science/Research
Classifier: License :: OSI Approved :: MIT License
Classifier: Operating System :: OS Independent
Classifier: Programming Language :: Python
Classifier: Programming Language :: Python :: 3
Classifier: Programming Language :: Python :: 3.10
Classifier: Programming Language :: Python :: 3.11
Classifier: Programming Language :: Python :: 3.12
Classifier: Programming Language :: Python :: 3.13
Classifier: Topic :: Scientific/Engineering
Classifier: Topic :: Software Development :: Libraries :: Python Modules
Requires-Python: <3.14,>=3.10
Requires-Dist: numba>=0.61
Requires-Dist: numpy>=2
